LICENSE
MANIFEST.in
README.md
requirements.txt
setup.py
langchain_serve.egg-info/PKG-INFO
langchain_serve.egg-info/SOURCES.txt
langchain_serve.egg-info/dependency_links.txt
langchain_serve.egg-info/entry_points.txt
langchain_serve.egg-info/not-zip-safe
langchain_serve.egg-info/requires.txt
langchain_serve.egg-info/top_level.txt
lcserve/Dockerfile
lcserve/__init__.py
lcserve/__main__.py
lcserve/agent-requirements.txt
lcserve/config.yml
lcserve/customgateway.Dockerfile
lcserve/customgateway_config.yml
lcserve/flow.py
lcserve/flow.yml
lcserve/playgroundgateway_config.yml
lcserve/requirements.txt
lcserve/servinggateway.Dockerfile
lcserve/servinggateway_config.yml
lcserve/apps/autogpt/__init__.py
lcserve/apps/autogpt/app.py
lcserve/apps/autogpt/helper.py
lcserve/apps/autogpt/requirements.txt
lcserve/apps/babyagi/__init__.py
lcserve/apps/babyagi/app.py
lcserve/apps/babyagi/babyagi.py
lcserve/apps/babyagi/requirements.txt
lcserve/apps/pandas_ai/api.py
lcserve/apps/pandas_ai/requirements.txt
lcserve/apps/pdf_qna/app.py
lcserve/apps/pdf_qna/chain.py
lcserve/apps/pdf_qna/requirements.txt
lcserve/backend/__init__.py
lcserve/backend/agentexecutor.py
lcserve/backend/decorators.py
lcserve/backend/gateway.py
lcserve/backend/nginx.conf
lcserve/backend/utils.py
lcserve/backend/playground/__init__.py
lcserve/backend/playground/app.py
lcserve/backend/playground/config.toml
lcserve/backend/playground/utils/__init__.py
lcserve/backend/playground/utils/helper.py
lcserve/backend/playground/utils/langchain_helper.py
lcserve/backend/playground/utils/talk.py
lcserve/backend/playground/utils/tools.py
lcserve/playground/__init__.py
lcserve/playground/autogpt/__init__.py
lcserve/playground/autogpt/playground.py
lcserve/playground/autogpt/user_input.py
lcserve/playground/babyagi/playground.py
lcserve/playground/babyagi/user_input.py
lcserve/playground/pandas_ai/__init__.py
lcserve/playground/pandas_ai/dataframe.py
lcserve/playground/pandas_ai/playground.py
lcserve/playground/pdf_qna/commands.md
lcserve/playground/pdf_qna/playground.py